sqlalchemy_bigquery/__init__.py
sqlalchemy_bigquery/_helpers.py
sqlalchemy_bigquery/_struct.py
sqlalchemy_bigquery/_types.py
sqlalchemy_bigquery/base.py
sqlalchemy_bigquery/geography.py
sqlalchemy_bigquery/parse_url.py
sqlalchemy_bigquery/requirements.py
sqlalchemy_bigquery/version.py
openmetadata_sqlalchemy_bigquery-1.2.0.dist-info/AUTHORS
openmetadata_sqlalchemy_bigquery-1.2.0.dist-info/LICENSE
openmetadata_sqlalchemy_bigquery-1.2.0.dist-info/METADATA
openmetadata_sqlalchemy_bigquery-1.2.0.dist-info/WHEEL
openmetadata_sqlalchemy_bigquery-1.2.0.dist-info/entry_points.txt
openmetadata_sqlalchemy_bigquery-1.2.0.dist-info/top_level.txt
openmetadata_sqlalchemy_bigquery-1.2.0.dist-info/RECORD
