Metadata-Version: 2.1
Name: openmetadata-sqlalchemy-bigquery
Version: 1.2.0
Summary: SQLAlchemy dialect for BigQuery by OpenMetadata
Home-page: https://github.com/open-metadata/OpenMetadata
Author: The OpenMetadata Committers
Author-email: googleapis-packages@google.com
License: UNKNOWN
Keywords: bigquery,sqlalchemy
Platform: Posix; MacOS X; Windows
Classifier: Development Status :: 5 - Production/Stable
Classifier: Intended Audience :: Developers
Classifier: License :: OSI Approved :: MIT License
Classifier: Programming Language :: Python
Classifier: Programming Language :: Python :: 3
Classifier: Programming Language :: Python :: 3.6
Classifier: Programming Language :: Python :: 3.7
Classifier: Programming Language :: Python :: 3.8
Classifier: Programming Language :: Python :: 3.9
Classifier: Operating System :: OS Independent
Classifier: Topic :: Database :: Front-Ends
Obsoletes: pybigquery
Requires-Python: >=3.6
License-File: LICENSE
License-File: AUTHORS
Requires-Dist: google-api-core (>=1.30.0)
Requires-Dist: google-auth (<3.0.0dev,>=1.25.0)
Requires-Dist: google-cloud-bigquery (<3.0.0dev,>=2.25.2)
Requires-Dist: sqlalchemy (<1.5.0dev,>=1.2.0)
Requires-Dist: future
Provides-Extra: alembic
Requires-Dist: alembic ; extra == 'alembic'
Provides-Extra: all
Requires-Dist: pytz ; extra == 'all'
Requires-Dist: packaging ; extra == 'all'
Requires-Dist: GeoAlchemy2 ; extra == 'all'
Requires-Dist: alembic ; extra == 'all'
Requires-Dist: shapely ; extra == 'all'
Provides-Extra: geography
Requires-Dist: GeoAlchemy2 ; extra == 'geography'
Requires-Dist: shapely ; extra == 'geography'
Provides-Extra: tests
Requires-Dist: packaging ; extra == 'tests'
Requires-Dist: pytz ; extra == 'tests'
